cv4beamanalysis/__init__.py
cv4beamanalysis/analyze.py
cv4beamanalysis/beam.py
cv4beamanalysis/main.py
cv4beamanalysis/number.py
cv4beamanalysis/relationships.py
cv4beamanalysis/yolo.py
cv4beamanalysis/models/__init__.py
cv4beamanalysis/models/features/data.yaml
cv4beamanalysis/models/features/weights/best.pt
cv4beamanalysis/models/features/weights/last.pt
cv4beamanalysis/models/number/charList.txt
cv4beamanalysis/models/number/checkpoint
cv4beamanalysis/models/number/snapshot-12.data-00000-of-00001
cv4beamanalysis/models/number/snapshot-12.index
cv4beamanalysis/models/number/snapshot-12.meta
cv4beamanalysis/models/number/summary.json
cv4beamanalysis/models/relationships/Beam-Load/keras_metadata.pb
cv4beamanalysis/models/relationships/Beam-Load/saved_model.pb
cv4beamanalysis/models/relationships/Beam-Load/variables/variables.data-00000-of-00001
cv4beamanalysis/models/relationships/Beam-Load/variables/variables.index
cv4beamanalysis/models/relationships/Beam-Support/keras_metadata.pb
cv4beamanalysis/models/relationships/Beam-Support/saved_model.pb
cv4beamanalysis/models/relationships/Beam-Support/variables/variables.data-00000-of-00001
cv4beamanalysis/models/relationships/Beam-Support/variables/variables.index
cv4beamanalysis/models/relationships/Element-Length/keras_metadata.pb
cv4beamanalysis/models/relationships/Element-Length/saved_model.pb
cv4beamanalysis/models/relationships/Element-Length/variables/variables.data-00000-of-00001
cv4beamanalysis/models/relationships/Element-Length/variables/variables.index
cv4beamanalysis/models/relationships/Length-Number/keras_metadata.pb
cv4beamanalysis/models/relationships/Length-Number/saved_model.pb
cv4beamanalysis/models/relationships/Length-Number/variables/variables.data-00000-of-00001
cv4beamanalysis/models/relationships/Length-Number/variables/variables.index
cv4beamanalysis/models/relationships/Length-Style/keras_metadata.pb
cv4beamanalysis/models/relationships/Length-Style/saved_model.pb
cv4beamanalysis-1.0.7.dist-info/LICENSE
cv4beamanalysis-1.0.7.dist-info/METADATA
cv4beamanalysis-1.0.7.dist-info/WHEEL
cv4beamanalysis-1.0.7.dist-info/top_level.txt
cv4beamanalysis-1.0.7.dist-info/RECORD
