Metadata-Version: 2.1
Name: cv4beamanalysis
Version: 1.0.7
Summary: A package to analyze handwritten beam diagrams
Author-email: Isaac Joffe <ijoffe@ualberta.ca>
Project-URL: Homepage, https://github.com/mqp2259/CV4BeamAnalysis
Project-URL: Issues, https://github.com/mqp2259/CV4BeamAnalysis/issues
Classifier: Programming Language :: Python :: 3
Classifier: License :: OSI Approved :: MIT License
Classifier: Operating System :: OS Independent
Requires-Python: >=3.10
License-File: LICENSE
